{
  "data": [
    {
      "date": "2026-04-23",
      "value": 1.0,
      "cash": 1.0,
      "stock": 0.0
    },
    {
      "date": "2023-07-21",
      "value": 0.5,
      "cash": 0.5,
      "stock": 0.0
    },
    {
      "date": "2022-07-20",
      "value": 39.01887,
      "cash": 3.54717,
      "stock": 35.4717
    },
    {
      "date": "2021-09-01",
      "value": 46.981308000000006,
      "cash": 4.271028,
      "stock": 42.710280000000004
    },
    {
      "date": "2020-10-06",
      "value": 1.221765,
      "cash": 1.221765,
      "stock": 0.0
    }
  ]
}