{
  "version": "1.0",
  "updated_at": "2026-05-16T18:06:34.656106+08:00",
  "stocks": [
    {
      "date": "2025-09-15",
      "twse": {
        "short_balance": 294399,
        "short_change": -3264,
        "margin_balance": 264210665000,
        "margin_change": -1404207000
      },
      "tpex": {
        "short_balance": 107966,
        "short_change": -850,
        "margin_balance": 106099143000,
        "margin_change": -174907000
      },
      "total_margin_balance": 370309808000,
      "total_margin_change": -1579114000,
      "total_short_balance": 402365,
      "total_short_change": -4114
    }
  ],
  "data": [
    {
      "date": "2025-09-15",
      "twse": {
        "short_balance": 294399,
        "short_change": -3264,
        "margin_balance": 264210665000,
        "margin_change": -1404207000
      },
      "tpex": {
        "short_balance": 107966,
        "short_change": -850,
        "margin_balance": 106099143000,
        "margin_change": -174907000
      },
      "total_margin_balance": 370309808000,
      "total_margin_change": -1579114000,
      "total_short_balance": 402365,
      "total_short_change": -4114
    }
  ]
}