{
  "stock_id": "6111",
  "name": "6111",
  "date": "2026-06-02",
  "close": 43.85,
  "health_score": 66,
  "signal": "Neutral",
  "institutional": {
    "foreign_buy_days": 0,
    "foreign_buy_ratio": 0.0,
    "trust_buy_days": 0,
    "dealer_buy_days": 0
  },
  "margin": {
    "margin_change": 2442.0,
    "short_change": 1.0,
    "short_margin_ratio": 0.04
  },
  "tdcc": {
    "big_holder_change": 39.69,
    "retail_holder_change": 0,
    "holder_concentration": 43.92
  },
  "main_force": {
    "cost": 46.62,
    "distance": -5.94,
    "trend": "DOWN"
  },
  "sector": {
    "name": "一般",
    "score": 80
  },
  "market_style": {
    "style": "Value",
    "score": 0
  },
  "events": [],
  "raw_signals": [],
  "data_version": "2026-06-02"
}