{
  "data": [
    {
      "date": "2026-03-31",
      "period": "2026-Q1",
      "value": -0.16,
      "eps": -0.16,
      "gm": 3.74,
      "om": -14.05,
      "nm": -12.84,
      "roe": -1.79,
      "roa": -0.84,
      "yoy": -40.74
    },
    {
      "date": "2025-12-31",
      "period": "2025-Q4",
      "value": -1.01,
      "eps": -1.01,
      "gm": 6.7,
      "om": -11.84,
      "nm": -21.55,
      "roe": -11.22,
      "roa": -5.32,
      "yoy": 17.44
    },
    {
      "date": "2025-09-30",
      "period": "2025-Q3",
      "value": -0.39,
      "eps": -0.39,
      "gm": 6.68,
      "om": -12.24,
      "nm": -11.25,
      "roe": -3.77,
      "roa": -1.87,
      "yoy": -40.0
    },
    {
      "date": "2025-06-30",
      "period": "2025-Q2",
      "value": -0.71,
      "eps": -0.71,
      "gm": 7.28,
      "om": -9.78,
      "nm": -30.61,
      "roe": -7.15,
      "roa": -3.45,
      "yoy": 208.7
    },
    {
      "date": "2025-03-31",
      "period": "2025-Q1",
      "value": -0.27,
      "eps": -0.27,
      "gm": 7.52,
      "om": -9.59,
      "nm": -23.63,
      "roe": -2.37,
      "roa": -1.22,
      "yoy": 58.82
    },
    {
      "date": "2024-12-31",
      "period": "2024-Q4",
      "value": -0.86,
      "eps": -0.86,
      "gm": 4.63,
      "om": -31.43,
      "nm": -20.18,
      "roe": -6.95,
      "roa": -3.71,
      "yoy": 0
    },
    {
      "date": "2024-09-30",
      "period": "2024-Q3",
      "value": -0.65,
      "eps": -0.65,
      "gm": 4.58,
      "om": -27.38,
      "nm": -20.23,
      "roe": -5.15,
      "roa": -2.86,
      "yoy": 0
    },
    {
      "date": "2024-06-30",
      "period": "2024-Q2",
      "value": -0.23,
      "eps": -0.23,
      "gm": 3.18,
      "om": -24.7,
      "nm": -11.25,
      "roe": -1.59,
      "roa": -0.93,
      "yoy": 0
    },
    {
      "date": "2024-03-31",
      "period": "2024-Q1",
      "value": -0.17,
      "eps": -0.17,
      "gm": 3.38,
      "om": -31.8,
      "nm": -16.91,
      "roe": -1.2,
      "roa": -0.69,
      "yoy": 0
    }
  ]
}