{
  "recent": [
    {
      "date": "2026-06-20",
      "percentage": 27.73,
      "r400": 43.15,
      "r1000": 27.73,
      "diff": 0.06
    },
    {
      "date": "2026-06-13",
      "percentage": 27.67,
      "r400": 44.42,
      "r1000": 27.67,
      "diff": -0.88
    },
    {
      "date": "2026-06-06",
      "percentage": 28.55,
      "r400": 42.97,
      "r1000": 28.55,
      "diff": 0.25
    },
    {
      "date": "2026-05-30",
      "percentage": 28.3,
      "r400": 44.8,
      "r1000": 28.3,
      "diff": -1.67
    },
    {
      "date": "2026-05-23",
      "percentage": 29.97,
      "r400": 45.06,
      "r1000": 29.97,
      "diff": 1.82
    },
    {
      "date": "2026-05-16",
      "percentage": 28.15,
      "r400": 45.45,
      "r1000": 28.15,
      "diff": 1.87
    },
    {
      "date": "2026-05-09",
      "percentage": 26.28,
      "r400": 43.3,
      "r1000": 26.28,
      "diff": -0.62
    },
    {
      "date": "2026-05-08",
      "percentage": 26.9,
      "r400": 41.5,
      "r1000": 26.9,
      "diff": -1.06
    },
    {
      "date": "2026-04-26",
      "percentage": 27.96,
      "r400": 42.03,
      "r1000": 27.96,
      "diff": -0.84
    },
    {
      "date": "2026-W16",
      "percentage": 28.8,
      "r400": 41.61,
      "r1000": 28.8,
      "diff": 0.27
    },
    {
      "date": "2026-W15",
      "percentage": 28.53,
      "r400": 41.46,
      "r1000": 28.53,
      "diff": -0.86
    },
    {
      "date": "2026-W14",
      "percentage": 29.39,
      "r400": 41.96,
      "r1000": 29.39,
      "diff": 1.82
    },
    {
      "date": "2026-W13",
      "percentage": 27.57,
      "r400": 41.41,
      "r1000": 27.57,
      "diff": -1.0
    },
    {
      "date": "2026-W12",
      "percentage": 28.57,
      "r400": 41.13,
      "r1000": 28.57,
      "diff": 0.84
    },
    {
      "date": "2026-W11",
      "percentage": 27.73,
      "r400": 40.37,
      "r1000": 27.73,
      "diff": -0.96
    },
    {
      "date": "2026-W10",
      "percentage": 28.69,
      "r400": 40.1,
      "r1000": 28.69,
      "diff": 0.78
    },
    {
      "date": "2026-W09",
      "percentage": 27.91,
      "r400": 39.48,
      "r1000": 27.91,
      "diff": -0.02
    },
    {
      "date": "2026-W07",
      "percentage": 27.93,
      "r400": 38.03,
      "r1000": 27.93,
      "diff": -0.47
    },
    {
      "date": "2026-W06",
      "percentage": 28.4,
      "r400": 38.21,
      "r1000": 28.4,
      "diff": -0.2
    },
    {
      "date": "2026-W05",
      "percentage": 28.6,
      "r400": 38.63,
      "r1000": 28.6,
      "diff": -0.17
    },
    {
      "date": "2026-W04",
      "percentage": 28.77,
      "r400": 39.02,
      "r1000": 28.77,
      "diff": 0.91
    },
    {
      "date": "2026-W03",
      "percentage": 27.86,
      "r400": 38.16,
      "r1000": 27.86,
      "diff": 1.68
    },
    {
      "date": "2026-W02",
      "percentage": 26.18,
      "r400": 37.49,
      "r1000": 26.18,
      "diff": 0.32
    },
    {
      "date": "2026-W01",
      "percentage": 25.86,
      "r400": 39.23,
      "r1000": 25.86,
      "diff": -2.56
    },
    {
      "date": "2025-W52",
      "percentage": 28.42,
      "r400": 38.92,
      "r1000": 28.42,
      "diff": -0.11
    },
    {
      "date": "2025-W51",
      "percentage": 28.53,
      "r400": 38.84,
      "r1000": 28.53,
      "diff": -0.24
    },
    {
      "date": "2025-W50",
      "percentage": 28.77,
      "r400": 38.75,
      "r1000": 28.77,
      "diff": -0.11
    },
    {
      "date": "2025-W49",
      "percentage": 28.88,
      "r400": 39.55,
      "r1000": 28.88,
      "diff": -0.74
    },
    {
      "date": "2025-W48",
      "percentage": 29.62,
      "r400": 39.5,
      "r1000": 29.62,
      "diff": 0.01
    },
    {
      "date": "2025-W47",
      "percentage": 29.61,
      "r400": 39.79,
      "r1000": 29.61,
      "diff": -0.02
    },
    {
      "date": "2025-W46",
      "percentage": 29.63,
      "r400": 39.85,
      "r1000": 29.63,
      "diff": -0.24
    },
    {
      "date": "2025-W45",
      "percentage": 29.87,
      "r400": 41.35,
      "r1000": 29.87,
      "diff": -1.75
    },
    {
      "date": "2025-W44",
      "percentage": 31.62,
      "r400": 42.33,
      "r1000": 31.62,
      "diff": -0.7
    },
    {
      "date": "2025-W43",
      "percentage": 32.32,
      "r400": 43.44,
      "r1000": 32.32,
      "diff": 0.05
    },
    {
      "date": "2025-W42",
      "percentage": 32.27,
      "r400": 43.65,
      "r1000": 32.27,
      "diff": 0.16
    },
    {
      "date": "2025-W41",
      "percentage": 32.11,
      "r400": 43.82,
      "r1000": 32.11,
      "diff": -0.05
    },
    {
      "date": "2025-W40",
      "percentage": 32.16,
      "r400": 43.91,
      "r1000": 32.16,
      "diff": -0.04
    },
    {
      "date": "2025-W39",
      "percentage": 32.2,
      "r400": 43.48,
      "r1000": 32.2,
      "diff": -1.52
    },
    {
      "date": "2025-W38",
      "percentage": 33.72,
      "r400": 44.86,
      "r1000": 33.72,
      "diff": 0.8
    },
    {
      "date": "2025-W37",
      "percentage": 32.92,
      "r400": 44.77,
      "r1000": 32.92,
      "diff": -0.15
    },
    {
      "date": "2025-W36",
      "percentage": 33.07,
      "r400": 45.4,
      "r1000": 33.07,
      "diff": -1.01
    },
    {
      "date": "2025-W35",
      "percentage": 34.08,
      "r400": 45.5,
      "r1000": 34.08,
      "diff": -0.11
    },
    {
      "date": "2025-W34",
      "percentage": 34.19,
      "r400": 45.62,
      "r1000": 34.19,
      "diff": 0.11
    },
    {
      "date": "2025-W33",
      "percentage": 34.08,
      "r400": 45.2,
      "r1000": 34.08,
      "diff": 1.37
    },
    {
      "date": "2025-W32",
      "percentage": 32.71,
      "r400": 44.18,
      "r1000": 32.71,
      "diff": 0.28
    },
    {
      "date": "2025-W31",
      "percentage": 32.43,
      "r400": 43.69,
      "r1000": 32.43,
      "diff": -0.05
    },
    {
      "date": "2025-W30",
      "percentage": 32.48,
      "r400": 43.72,
      "r1000": 32.48,
      "diff": -1.05
    },
    {
      "date": "2025-W29",
      "percentage": 33.53,
      "r400": 44.63,
      "r1000": 33.53,
      "diff": 0.98
    },
    {
      "date": "2025-W28",
      "percentage": 32.55,
      "r400": 44.1,
      "r1000": 32.55,
      "diff": 0.09
    },
    {
      "date": "2025-W27",
      "percentage": 32.46,
      "r400": 44.62,
      "r1000": 32.46,
      "diff": 1.59
    },
    {
      "date": "2025-W26",
      "percentage": 30.87,
      "r400": 44.19,
      "r1000": 30.87,
      "diff": 0.0
    },
    {
      "date": "2025-W25",
      "percentage": 30.87,
      "r400": 43.42,
      "r1000": 30.87,
      "diff": -0.42
    }
  ]
}