{
  "data": [
    {
      "date": "2026-04-01",
      "period": "2026-04",
      "value": 19603.0,
      "yoy": 0.92
    },
    {
      "date": "2026-03-01",
      "period": "2026-03",
      "value": 16608.0,
      "yoy": 10.39
    },
    {
      "date": "2026-02-01",
      "period": "2026-02",
      "value": 15309.0,
      "yoy": 1.4
    },
    {
      "date": "2026-01-01",
      "period": "2026-01",
      "value": 23028.0,
      "yoy": 32.88
    },
    {
      "date": "2025-12-01",
      "period": "2025-12",
      "value": 23204.0,
      "yoy": 15.51
    },
    {
      "date": "2025-11-01",
      "period": "2025-11",
      "value": 20141.0,
      "yoy": 43.81
    },
    {
      "date": "2025-10-01",
      "period": "2025-10",
      "value": 17141.0,
      "yoy": -0.78
    },
    {
      "date": "2025-09-01",
      "period": "2025-09",
      "value": 19535.0,
      "yoy": 55.78
    },
    {
      "date": "2025-08-01",
      "period": "2025-08",
      "value": 17635.0,
      "yoy": 9.71
    },
    {
      "date": "2025-07-01",
      "period": "2025-07",
      "value": 24492.0,
      "yoy": 55.44
    },
    {
      "date": "2025-06-01",
      "period": "2025-06",
      "value": 14558.0,
      "yoy": 59.73
    },
    {
      "date": "2025-05-01",
      "period": "2025-05",
      "value": 18735.0,
      "yoy": 44.1
    },
    {
      "date": "2025-04-01",
      "period": "2025-04",
      "value": 19424.0,
      "yoy": 28.14
    },
    {
      "date": "2025-03-01",
      "period": "2025-03",
      "value": 15045.0,
      "yoy": -1.88
    },
    {
      "date": "2025-02-01",
      "period": "2025-02",
      "value": 15097.0,
      "yoy": 79.56
    },
    {
      "date": "2025-01-01",
      "period": "2025-01",
      "value": 17330.0,
      "yoy": 49.1
    },
    {
      "date": "2024-12-01",
      "period": "2024-12",
      "value": 20089.0,
      "yoy": 82.52771215700527
    },
    {
      "date": "2024-11-01",
      "period": "2024-11",
      "value": 14005.0,
      "yoy": 51.68417632405502
    },
    {
      "date": "2024-10-01",
      "period": "2024-10",
      "value": 17276.0,
      "yoy": -3.502206334133944
    },
    {
      "date": "2024-09-01",
      "period": "2024-09",
      "value": 12540.0,
      "yoy": 84.14096916299559
    },
    {
      "date": "2024-08-01",
      "period": "2024-08",
      "value": 16074.0,
      "yoy": 129.3664383561644
    },
    {
      "date": "2024-07-01",
      "period": "2024-07",
      "value": 15757.0,
      "yoy": 113.22056833558864
    },
    {
      "date": "2024-06-01",
      "period": "2024-06",
      "value": 9114.0,
      "yoy": 76.14998067259374
    },
    {
      "date": "2024-05-01",
      "period": "2024-05",
      "value": 13001.0,
      "yoy": -54.764969903622
    },
    {
      "date": "2024-04-01",
      "period": "2024-04",
      "value": 15158.0,
      "yoy": 232.5581395348837
    },
    {
      "date": "2024-03-01",
      "period": "2024-03",
      "value": 15334.0,
      "yoy": 262.24899598393574
    },
    {
      "date": "2024-02-01",
      "period": "2024-02",
      "value": 8408.0,
      "yoy": 212.79761904761904
    },
    {
      "date": "2024-01-01",
      "period": "2024-01",
      "value": 11623.0,
      "yoy": 199.1763191763192
    }
  ]
}