{
  "symbol": "1470",
  "updated_at": "2026-06-05",
  "lines": [
    {
      "id": "H_32",
      "type": "high",
      "price": 27.6,
      "start_idx": 32,
      "start_date": "2025-05-05",
      "end_idx": null,
      "end_date": null,
      "broken": false,
      "strength": 1
    },
    {
      "id": "L_100",
      "type": "low",
      "price": 19.55,
      "start_idx": 100,
      "start_date": "2025-08-27",
      "end_idx": null,
      "end_date": null,
      "broken": false,
      "strength": 1
    },
    {
      "id": "L_119",
      "type": "low",
      "price": 21.4,
      "start_idx": 119,
      "start_date": "2025-09-30",
      "end_idx": 187,
      "end_date": "2026-03-16",
      "broken": true,
      "strength": 1
    },
    {
      "id": "H_125",
      "type": "high",
      "price": 23.5,
      "start_idx": 125,
      "start_date": "2025-10-13",
      "end_idx": 174,
      "end_date": "2026-02-24",
      "broken": true,
      "strength": 1
    },
    {
      "id": "L_138",
      "type": "low",
      "price": 21.75,
      "start_idx": 138,
      "start_date": "2025-11-12",
      "end_idx": 187,
      "end_date": "2026-03-16",
      "broken": true,
      "strength": 1
    },
    {
      "id": "H_138",
      "type": "high",
      "price": 22.8,
      "start_idx": 138,
      "start_date": "2025-11-12",
      "end_idx": 144,
      "end_date": "2025-11-25",
      "broken": true,
      "strength": 1
    },
    {
      "id": "H_144",
      "type": "high",
      "price": 22.9,
      "start_idx": 144,
      "start_date": "2025-11-25",
      "end_idx": 150,
      "end_date": "2025-12-12",
      "broken": true,
      "strength": 1
    },
    {
      "id": "H_150",
      "type": "high",
      "price": 23.9,
      "start_idx": 150,
      "start_date": "2025-12-12",
      "end_idx": null,
      "end_date": null,
      "broken": false,
      "strength": 1
    },
    {
      "id": "L_153",
      "type": "low",
      "price": 22.05,
      "start_idx": 153,
      "start_date": "2025-12-17",
      "end_idx": 187,
      "end_date": "2026-03-16",
      "broken": true,
      "strength": 1
    },
    {
      "id": "L_163",
      "type": "low",
      "price": 21.9,
      "start_idx": 163,
      "start_date": "2026-01-21",
      "end_idx": 187,
      "end_date": "2026-03-16",
      "broken": true,
      "strength": 1
    },
    {
      "id": "H_164",
      "type": "high",
      "price": 24.1,
      "start_idx": 164,
      "start_date": "2026-01-22",
      "end_idx": null,
      "end_date": null,
      "broken": false,
      "strength": 1
    },
    {
      "id": "H_174",
      "type": "high",
      "price": 24.6,
      "start_idx": 174,
      "start_date": "2026-02-24",
      "end_idx": null,
      "end_date": null,
      "broken": false,
      "strength": 1
    },
    {
      "id": "H_183",
      "type": "high",
      "price": 24.35,
      "start_idx": 183,
      "start_date": "2026-03-10",
      "end_idx": null,
      "end_date": null,
      "broken": false,
      "strength": 1
    },
    {
      "id": "L_187",
      "type": "low",
      "price": 21.2,
      "start_idx": 187,
      "start_date": "2026-03-16",
      "end_idx": 228,
      "end_date": "2026-05-19",
      "broken": true,
      "strength": 1
    },
    {
      "id": "H_189",
      "type": "high",
      "price": 23.85,
      "start_idx": 189,
      "start_date": "2026-03-18",
      "end_idx": null,
      "end_date": null,
      "broken": false,
      "strength": 1
    },
    {
      "id": "L_196",
      "type": "low",
      "price": 21.4,
      "start_idx": 196,
      "start_date": "2026-03-30",
      "end_idx": 228,
      "end_date": "2026-05-19",
      "broken": true,
      "strength": 1
    },
    {
      "id": "H_206",
      "type": "high",
      "price": 23.95,
      "start_idx": 206,
      "start_date": "2026-04-15",
      "end_idx": null,
      "end_date": null,
      "broken": false,
      "strength": 1
    },
    {
      "id": "H_211",
      "type": "high",
      "price": 23.95,
      "start_idx": 211,
      "start_date": "2026-04-22",
      "end_idx": null,
      "end_date": null,
      "broken": false,
      "strength": 1
    },
    {
      "id": "H_227",
      "type": "high",
      "price": 22.55,
      "start_idx": 227,
      "start_date": "2026-05-18",
      "end_idx": 237,
      "end_date": "2026-06-01",
      "broken": true,
      "strength": 1
    },
    {
      "id": "L_229",
      "type": "low",
      "price": 20.5,
      "start_idx": 229,
      "start_date": "2026-05-20",
      "end_idx": null,
      "end_date": null,
      "broken": false,
      "strength": 1
    }
  ],
  "events": [
    {
      "type": "BOS_UP",
      "price": 22.8,
      "idx": 144,
      "date": "2025-11-25"
    },
    {
      "type": "BOS_UP",
      "price": 22.9,
      "idx": 150,
      "date": "2025-12-12"
    },
    {
      "type": "BOS_UP",
      "price": 23.5,
      "idx": 174,
      "date": "2026-02-24"
    },
    {
      "type": "CHOCH_DOWN",
      "price": 21.4,
      "idx": 187,
      "date": "2026-03-16"
    },
    {
      "type": "CHOCH_DOWN",
      "price": 21.75,
      "idx": 187,
      "date": "2026-03-16"
    },
    {
      "type": "CHOCH_DOWN",
      "price": 22.05,
      "idx": 187,
      "date": "2026-03-16"
    },
    {
      "type": "CHOCH_DOWN",
      "price": 21.9,
      "idx": 187,
      "date": "2026-03-16"
    },
    {
      "type": "CHOCH_DOWN",
      "price": 21.2,
      "idx": 228,
      "date": "2026-05-19"
    },
    {
      "type": "CHOCH_DOWN",
      "price": 21.4,
      "idx": 228,
      "date": "2026-05-19"
    },
    {
      "type": "BOS_UP",
      "price": 22.55,
      "idx": 237,
      "date": "2026-06-01"
    }
  ]
}