{
  "symbol": "2924",
  "updated_at": "2026-06-08",
  "lines": [
    {
      "id": "H_10",
      "type": "high",
      "price": 33.6,
      "start_idx": 10,
      "start_date": "2025-04-02",
      "end_idx": null,
      "end_date": null,
      "broken": false,
      "strength": 1
    },
    {
      "id": "H_16",
      "type": "high",
      "price": 31.95,
      "start_idx": 16,
      "start_date": "2025-04-14",
      "end_idx": null,
      "end_date": null,
      "broken": false,
      "strength": 1
    },
    {
      "id": "H_32",
      "type": "high",
      "price": 31.45,
      "start_idx": 32,
      "start_date": "2025-05-15",
      "end_idx": null,
      "end_date": null,
      "broken": false,
      "strength": 1
    },
    {
      "id": "H_38",
      "type": "high",
      "price": 30.75,
      "start_idx": 38,
      "start_date": "2025-05-23",
      "end_idx": null,
      "end_date": null,
      "broken": false,
      "strength": 1
    },
    {
      "id": "H_86",
      "type": "high",
      "price": 30.5,
      "start_idx": 86,
      "start_date": "2025-09-04",
      "end_idx": null,
      "end_date": null,
      "broken": false,
      "strength": 1
    },
    {
      "id": "H_111",
      "type": "high",
      "price": 28.7,
      "start_idx": 111,
      "start_date": "2025-11-20",
      "end_idx": null,
      "end_date": null,
      "broken": false,
      "strength": 1
    },
    {
      "id": "L_126",
      "type": "low",
      "price": 18.8,
      "start_idx": 126,
      "start_date": "2026-01-05",
      "end_idx": 150,
      "end_date": "2026-02-23",
      "broken": true,
      "strength": 1
    },
    {
      "id": "H_135",
      "type": "high",
      "price": 20.35,
      "start_idx": 135,
      "start_date": "2026-01-22",
      "end_idx": 169,
      "end_date": "2026-04-09",
      "broken": true,
      "strength": 1
    },
    {
      "id": "L_143",
      "type": "low",
      "price": 18.05,
      "start_idx": 143,
      "start_date": "2026-02-03",
      "end_idx": 165,
      "end_date": "2026-03-30",
      "broken": true,
      "strength": 1
    },
    {
      "id": "L_154",
      "type": "low",
      "price": 17.45,
      "start_idx": 154,
      "start_date": "2026-03-02",
      "end_idx": 165,
      "end_date": "2026-03-30",
      "broken": true,
      "strength": 1
    },
    {
      "id": "H_158",
      "type": "high",
      "price": 20.05,
      "start_idx": 158,
      "start_date": "2026-03-13",
      "end_idx": 169,
      "end_date": "2026-04-09",
      "broken": true,
      "strength": 1
    },
    {
      "id": "H_159",
      "type": "high",
      "price": 20.05,
      "start_idx": 159,
      "start_date": "2026-03-16",
      "end_idx": 169,
      "end_date": "2026-04-09",
      "broken": true,
      "strength": 1
    },
    {
      "id": "H_160",
      "type": "high",
      "price": 20.05,
      "start_idx": 160,
      "start_date": "2026-03-17",
      "end_idx": 169,
      "end_date": "2026-04-09",
      "broken": true,
      "strength": 1
    },
    {
      "id": "H_161",
      "type": "high",
      "price": 20.05,
      "start_idx": 161,
      "start_date": "2026-03-18",
      "end_idx": 169,
      "end_date": "2026-04-09",
      "broken": true,
      "strength": 1
    },
    {
      "id": "L_167",
      "type": "low",
      "price": 16.0,
      "start_idx": 167,
      "start_date": "2026-04-07",
      "end_idx": 183,
      "end_date": "2026-05-21",
      "broken": true,
      "strength": 1
    },
    {
      "id": "H_175",
      "type": "high",
      "price": 22.45,
      "start_idx": 175,
      "start_date": "2026-04-28",
      "end_idx": null,
      "end_date": null,
      "broken": false,
      "strength": 1
    },
    {
      "id": "L_185",
      "type": "low",
      "price": 14.75,
      "start_idx": 185,
      "start_date": "2026-05-25",
      "end_idx": null,
      "end_date": null,
      "broken": false,
      "strength": 1
    },
    {
      "id": "H_185",
      "type": "high",
      "price": 16.9,
      "start_idx": 185,
      "start_date": "2026-05-25",
      "end_idx": 193,
      "end_date": "2026-06-04",
      "broken": true,
      "strength": 1
    }
  ],
  "events": [
    {
      "type": "CHOCH_DOWN",
      "price": 18.8,
      "idx": 150,
      "date": "2026-02-23"
    },
    {
      "type": "CHOCH_DOWN",
      "price": 18.05,
      "idx": 165,
      "date": "2026-03-30"
    },
    {
      "type": "CHOCH_DOWN",
      "price": 17.45,
      "idx": 165,
      "date": "2026-03-30"
    },
    {
      "type": "BOS_UP",
      "price": 20.35,
      "idx": 169,
      "date": "2026-04-09"
    },
    {
      "type": "BOS_UP",
      "price": 20.05,
      "idx": 169,
      "date": "2026-04-09"
    },
    {
      "type": "BOS_UP",
      "price": 20.05,
      "idx": 169,
      "date": "2026-04-09"
    },
    {
      "type": "BOS_UP",
      "price": 20.05,
      "idx": 169,
      "date": "2026-04-09"
    },
    {
      "type": "BOS_UP",
      "price": 20.05,
      "idx": 169,
      "date": "2026-04-09"
    },
    {
      "type": "CHOCH_DOWN",
      "price": 16.0,
      "idx": 183,
      "date": "2026-05-21"
    },
    {
      "type": "BOS_UP",
      "price": 16.9,
      "idx": 193,
      "date": "2026-06-04"
    }
  ]
}