{
  "symbol": "3443",
  "updated_at": "2026-05-08",
  "lines": [
    {
      "id": "L_37",
      "type": "low",
      "price": 853.0,
      "start_idx": 37,
      "end_idx": null,
      "broken": false,
      "strength": 1
    },
    {
      "id": "L_46",
      "type": "low",
      "price": 918.0,
      "start_idx": 46,
      "end_idx": null,
      "broken": false,
      "strength": 1
    },
    {
      "id": "L_85",
      "type": "low",
      "price": 1065.0,
      "start_idx": 85,
      "end_idx": null,
      "broken": false,
      "strength": 1
    },
    {
      "id": "L_86",
      "type": "low",
      "price": 1065.0,
      "start_idx": 86,
      "end_idx": null,
      "broken": false,
      "strength": 1
    },
    {
      "id": "L_87",
      "type": "low",
      "price": 1065.0,
      "start_idx": 87,
      "end_idx": null,
      "broken": false,
      "strength": 1
    },
    {
      "id": "L_88",
      "type": "low",
      "price": 1065.0,
      "start_idx": 88,
      "end_idx": null,
      "broken": false,
      "strength": 1
    },
    {
      "id": "L_130",
      "type": "low",
      "price": 1160.0,
      "start_idx": 130,
      "end_idx": null,
      "broken": false,
      "strength": 1
    },
    {
      "id": "L_157",
      "type": "low",
      "price": 1255.0,
      "start_idx": 157,
      "end_idx": null,
      "broken": false,
      "strength": 1
    },
    {
      "id": "H_171",
      "type": "high",
      "price": 1675.0,
      "start_idx": 171,
      "end_idx": 182,
      "broken": true,
      "strength": 1
    },
    {
      "id": "L_177",
      "type": "low",
      "price": 1440.0,
      "start_idx": 177,
      "end_idx": null,
      "broken": false,
      "strength": 1
    },
    {
      "id": "L_193",
      "type": "low",
      "price": 1850.0,
      "start_idx": 193,
      "end_idx": null,
      "broken": false,
      "strength": 1
    },
    {
      "id": "H_198",
      "type": "high",
      "price": 2260.0,
      "start_idx": 198,
      "end_idx": 208,
      "broken": true,
      "strength": 1
    },
    {
      "id": "H_208",
      "type": "high",
      "price": 2275.0,
      "start_idx": 208,
      "end_idx": 222,
      "broken": true,
      "strength": 1
    },
    {
      "id": "L_211",
      "type": "low",
      "price": 2010.0,
      "start_idx": 211,
      "end_idx": null,
      "broken": false,
      "strength": 1
    },
    {
      "id": "L_214",
      "type": "low",
      "price": 2010.0,
      "start_idx": 214,
      "end_idx": null,
      "broken": false,
      "strength": 1
    },
    {
      "id": "H_224",
      "type": "high",
      "price": 2490.0,
      "start_idx": 224,
      "end_idx": 230,
      "broken": true,
      "strength": 1
    },
    {
      "id": "H_236",
      "type": "high",
      "price": 2725.0,
      "start_idx": 236,
      "end_idx": 253,
      "broken": true,
      "strength": 1
    },
    {
      "id": "H_243",
      "type": "high",
      "price": 2705.0,
      "start_idx": 243,
      "end_idx": 253,
      "broken": true,
      "strength": 1
    },
    {
      "id": "L_245",
      "type": "low",
      "price": 2340.0,
      "start_idx": 245,
      "end_idx": 256,
      "broken": true,
      "strength": 1
    },
    {
      "id": "H_253",
      "type": "high",
      "price": 2770.0,
      "start_idx": 253,
      "end_idx": 282,
      "broken": true,
      "strength": 1
    },
    {
      "id": "L_259",
      "type": "low",
      "price": 2190.0,
      "start_idx": 259,
      "end_idx": 275,
      "broken": true,
      "strength": 1
    },
    {
      "id": "H_268",
      "type": "high",
      "price": 2645.0,
      "start_idx": 268,
      "end_idx": 280,
      "broken": true,
      "strength": 1
    },
    {
      "id": "L_275",
      "type": "low",
      "price": 2165.0,
      "start_idx": 275,
      "end_idx": null,
      "broken": false,
      "strength": 1
    }
  ],
  "events": [
    {
      "type": "BOS_UP",
      "price": 1675.0,
      "idx": 182,
      "date": "2025-11-06"
    },
    {
      "type": "BOS_UP",
      "price": 2260.0,
      "idx": 208,
      "date": "2025-12-12"
    },
    {
      "type": "BOS_UP",
      "price": 2275.0,
      "idx": 222,
      "date": "2026-01-05"
    },
    {
      "type": "BOS_UP",
      "price": 2490.0,
      "idx": 230,
      "date": "2026-01-15"
    },
    {
      "type": "BOS_UP",
      "price": 2725.0,
      "idx": 253,
      "date": "2026-02-26"
    },
    {
      "type": "BOS_UP",
      "price": 2705.0,
      "idx": 253,
      "date": "2026-02-26"
    },
    {
      "type": "CHOCH_DOWN",
      "price": 2340.0,
      "idx": 256,
      "date": "2026-03-04"
    },
    {
      "type": "CHOCH_DOWN",
      "price": 2190.0,
      "idx": 275,
      "date": "2026-03-31"
    },
    {
      "type": "BOS_UP",
      "price": 2645.0,
      "idx": 280,
      "date": "2026-04-09"
    },
    {
      "type": "BOS_UP",
      "price": 2770.0,
      "idx": 282,
      "date": "2026-04-13"
    }
  ]
}