{
  "symbol": "4572",
  "updated_at": "2026-06-16",
  "lines": [
    {
      "id": "H_34",
      "type": "high",
      "price": 192.0,
      "start_idx": 34,
      "start_date": "2025-05-15",
      "end_idx": null,
      "end_date": null,
      "broken": false,
      "strength": 1
    },
    {
      "id": "H_113",
      "type": "high",
      "price": 181.5,
      "start_idx": 113,
      "start_date": "2025-09-04",
      "end_idx": null,
      "end_date": null,
      "broken": false,
      "strength": 1
    },
    {
      "id": "H_120",
      "type": "high",
      "price": 178.5,
      "start_idx": 120,
      "start_date": "2025-09-15",
      "end_idx": null,
      "end_date": null,
      "broken": false,
      "strength": 1
    },
    {
      "id": "H_136",
      "type": "high",
      "price": 177.5,
      "start_idx": 136,
      "start_date": "2025-10-09",
      "end_idx": null,
      "end_date": null,
      "broken": false,
      "strength": 1
    },
    {
      "id": "L_156",
      "type": "low",
      "price": 140.0,
      "start_idx": 156,
      "start_date": "2025-11-10",
      "end_idx": 231,
      "end_date": "2026-03-09",
      "broken": true,
      "strength": 1
    },
    {
      "id": "L_163",
      "type": "low",
      "price": 140.5,
      "start_idx": 163,
      "start_date": "2025-11-19",
      "end_idx": 231,
      "end_date": "2026-03-09",
      "broken": true,
      "strength": 1
    },
    {
      "id": "H_173",
      "type": "high",
      "price": 159.0,
      "start_idx": 173,
      "start_date": "2025-12-03",
      "end_idx": null,
      "end_date": null,
      "broken": false,
      "strength": 1
    },
    {
      "id": "H_176",
      "type": "high",
      "price": 159.0,
      "start_idx": 176,
      "start_date": "2025-12-08",
      "end_idx": null,
      "end_date": null,
      "broken": false,
      "strength": 1
    },
    {
      "id": "H_188",
      "type": "high",
      "price": 158.5,
      "start_idx": 188,
      "start_date": "2025-12-24",
      "end_idx": null,
      "end_date": null,
      "broken": false,
      "strength": 1
    },
    {
      "id": "H_189",
      "type": "high",
      "price": 158.5,
      "start_idx": 189,
      "start_date": "2025-12-26",
      "end_idx": null,
      "end_date": null,
      "broken": false,
      "strength": 1
    },
    {
      "id": "L_197",
      "type": "low",
      "price": 147.5,
      "start_idx": 197,
      "start_date": "2026-01-08",
      "end_idx": 212,
      "end_date": "2026-01-29",
      "broken": true,
      "strength": 1
    },
    {
      "id": "H_200",
      "type": "high",
      "price": 153.5,
      "start_idx": 200,
      "start_date": "2026-01-13",
      "end_idx": null,
      "end_date": null,
      "broken": false,
      "strength": 1
    },
    {
      "id": "H_204",
      "type": "high",
      "price": 153.5,
      "start_idx": 204,
      "start_date": "2026-01-19",
      "end_idx": null,
      "end_date": null,
      "broken": false,
      "strength": 1
    },
    {
      "id": "L_214",
      "type": "low",
      "price": 141.5,
      "start_idx": 214,
      "start_date": "2026-02-02",
      "end_idx": 231,
      "end_date": "2026-03-09",
      "broken": true,
      "strength": 1
    },
    {
      "id": "L_218",
      "type": "low",
      "price": 141.5,
      "start_idx": 218,
      "start_date": "2026-02-06",
      "end_idx": 231,
      "end_date": "2026-03-09",
      "broken": true,
      "strength": 1
    },
    {
      "id": "H_223",
      "type": "high",
      "price": 150.0,
      "start_idx": 223,
      "start_date": "2026-02-24",
      "end_idx": 270,
      "end_date": "2026-05-06",
      "broken": true,
      "strength": 1
    },
    {
      "id": "L_231",
      "type": "low",
      "price": 138.0,
      "start_idx": 231,
      "start_date": "2026-03-09",
      "end_idx": null,
      "end_date": null,
      "broken": false,
      "strength": 1
    },
    {
      "id": "H_233",
      "type": "high",
      "price": 149.5,
      "start_idx": 233,
      "start_date": "2026-03-11",
      "end_idx": 270,
      "end_date": "2026-05-06",
      "broken": true,
      "strength": 1
    },
    {
      "id": "H_247",
      "type": "high",
      "price": 146.5,
      "start_idx": 247,
      "start_date": "2026-03-31",
      "end_idx": 259,
      "end_date": "2026-04-20",
      "broken": true,
      "strength": 1
    },
    {
      "id": "L_250",
      "type": "low",
      "price": 138.5,
      "start_idx": 250,
      "start_date": "2026-04-07",
      "end_idx": null,
      "end_date": null,
      "broken": false,
      "strength": 1
    },
    {
      "id": "H_259",
      "type": "high",
      "price": 148.0,
      "start_idx": 259,
      "start_date": "2026-04-20",
      "end_idx": 269,
      "end_date": "2026-05-05",
      "broken": true,
      "strength": 1
    },
    {
      "id": "H_260",
      "type": "high",
      "price": 148.0,
      "start_idx": 260,
      "start_date": "2026-04-21",
      "end_idx": 269,
      "end_date": "2026-05-05",
      "broken": true,
      "strength": 1
    },
    {
      "id": "H_270",
      "type": "high",
      "price": 151.0,
      "start_idx": 270,
      "start_date": "2026-05-06",
      "end_idx": null,
      "end_date": null,
      "broken": false,
      "strength": 1
    },
    {
      "id": "L_274",
      "type": "low",
      "price": 142.0,
      "start_idx": 274,
      "start_date": "2026-05-12",
      "end_idx": null,
      "end_date": null,
      "broken": false,
      "strength": 1
    },
    {
      "id": "L_275",
      "type": "low",
      "price": 142.0,
      "start_idx": 275,
      "start_date": "2026-05-13",
      "end_idx": null,
      "end_date": null,
      "broken": false,
      "strength": 1
    },
    {
      "id": "L_284",
      "type": "low",
      "price": 141.0,
      "start_idx": 284,
      "start_date": "2026-05-26",
      "end_idx": null,
      "end_date": null,
      "broken": false,
      "strength": 1
    },
    {
      "id": "H_287",
      "type": "high",
      "price": 151.5,
      "start_idx": 287,
      "start_date": "2026-05-29",
      "end_idx": null,
      "end_date": null,
      "broken": false,
      "strength": 1
    },
    {
      "id": "L_293",
      "type": "low",
      "price": 136.0,
      "start_idx": 293,
      "start_date": "2026-06-08",
      "end_idx": null,
      "end_date": null,
      "broken": false,
      "strength": 1
    }
  ],
  "events": [
    {
      "type": "CHOCH_DOWN",
      "price": 147.5,
      "idx": 212,
      "date": "2026-01-29"
    },
    {
      "type": "CHOCH_DOWN",
      "price": 140.0,
      "idx": 231,
      "date": "2026-03-09"
    },
    {
      "type": "CHOCH_DOWN",
      "price": 140.5,
      "idx": 231,
      "date": "2026-03-09"
    },
    {
      "type": "CHOCH_DOWN",
      "price": 141.5,
      "idx": 231,
      "date": "2026-03-09"
    },
    {
      "type": "CHOCH_DOWN",
      "price": 141.5,
      "idx": 231,
      "date": "2026-03-09"
    },
    {
      "type": "BOS_UP",
      "price": 146.5,
      "idx": 259,
      "date": "2026-04-20"
    },
    {
      "type": "BOS_UP",
      "price": 148.0,
      "idx": 269,
      "date": "2026-05-05"
    },
    {
      "type": "BOS_UP",
      "price": 148.0,
      "idx": 269,
      "date": "2026-05-05"
    },
    {
      "type": "BOS_UP",
      "price": 150.0,
      "idx": 270,
      "date": "2026-05-06"
    },
    {
      "type": "BOS_UP",
      "price": 149.5,
      "idx": 270,
      "date": "2026-05-06"
    }
  ]
}